Workbook
Name Eski_Ciro: Revenue!#REF!

Sheet Inputs
A1: FY2025 plan — assumptions
A2: Assumption | B2: Value
A3: Opening customers | B3: 1200
A4: Monthly new customers | B4: 85
A5: Monthly churn rate | B5: 0.021
A6: ARPU (TRY/month) | B6: 480
A7: Gross margin | B7: 0.62
A8: Headcount | B8: 6
A9: Average salary (TRY/month) | B9: 48000
A10: Marketing (TRY/month) | B10: 60000
A11: Office and other (TRY/month) | B11: 35000
A12: FX rate TRY/EUR | B12: 38.4

Sheet Revenue
A1: Monthly build
A3: Month | B3: Jan | C3: Feb | D3: Mar | E3: Apr | F3: May | G3: Jun | H3: Jul | I3: Aug | J3: Sep | K3: Oct | L3: Nov | M3: Dec
A5: Opening customers | B5: =Inputs!$B$3 | C5: =B9 | D5: =C9 | E5: =D9 | F5: =E9 | G5: =F9 | H5: =G9 | I5: =H9 | J5: =I9 | ... M5: =L9
A6: New customers | B6: =Inputs!$B$4 | C6: =Inputs!$B$4 | D6: =Inputs!$B$4 | E6: =Inputs!$B$4 | F6: =Inputs!$B$4 | G6: =Inputs!$B$4 | H6: =Inputs!$B$4 | I6: =Inputs!$B$4 | ... M6: =Inputs!$B$4
A7: Churned customers | B7: =-B5*Inputs!$B$5 | C7: =-C5*Inputs!$B$5 | D7: =-D5*Inputs!$B$5 | E7: =-E5*Inputs!$B$5 | F7: =-F5*Inputs!$B$5 | G7: =-G5*Inputs!$B$5 | H7: =-H5*Inputs!$B$5 | I7: =-I5*Inputs!$B$5 | ... M7: =-M5*Inputs!$B$5
A9: Ending customers | B9: =B5+B6+B7 | C9: =C5+C6+C7 | D9: =D5+D6+D7 | E9: =E5+E6+E7 | F9: =F5+F6+F7 | G9: =G5+G6+G7 | H9: =H5+H6+H7 | I9: =I5+I6+I7 | ... M9: =M5+M6+M7
A11: ARPU | B11: =Inputs!$B$6 | C11: =Inputs!$B$6 | D11: =Inputs!$B$6 | E11: =Inputs!$B$6 | F11: =Inputs!$B$6*1.06 | G11: =Inputs!$B$6 | H11: =Inputs!$B$6 | I11: =Inputs!$B$6 | J11: =Inputs!$B$6 | K11: =Inputs!$B$6 | L11: =Inputs!$B$6 | M11: =Inputs!$B$6
A12: Revenue | B12: =B9*B11 | C12: =C9*C11 | D12: =D9*D11 | E12: =E9*E11 | F12: =F9*F11 | G12: =G9*G11 | H12: 762000 | I12: =I9*I11 | J12: =J9*J11 | K12: =K9*K11 | L12: =L9*L11 | M12: =M9*M11
A13: Gross profit | B13: =B12*Inputs!$B$7 | C13: =C12*Inputs!$B$7 | D13: =D12*Inputs!$B$7 | E13: =E12*Inputs!$B$7 | F13: =F12*Inputs!$B$7 | G13: =G12*Inputs!$B$7 | H13: =H12*Inputs!$B$7 | I13: =I12*Inputs!$B$7 | J13: =J12*Inputs!$B$7 | K13: =K12*0.55 | L13: =L12*Inputs!$B$7 | M13: =M12*Inputs!$B$7
A15: Total revenue | B15: =SUM(B12:K12)

Sheet Costs
A1: Operating cost
A3: Cost line | B3: TRY per month
A4: Salaries | B4: =Inputs!$B$8*Inputs!$B$9
A5: Marketing | B5: =Inputs!$B$10
A6: Office and other | B6: =Inputs!$B$11
A7: Cloud hosting | B7: =Inputs!$B$3*13
A8: Tooling per seat | B8: =Inputs!$B$8*1800
A9: Software licences | B9: =Inputs!$B$8*42*Inputs!$B$12
A10: Travel | B10: =Inputs!$B$10*0.08
A11: Recruitment | B11: 18000
A12: Legal and audit | B12: 12000
A13: Total monthly cost | B13: =SUM(B4:B11)
A15: Annual cost | B15: =B13*12

Sheet Summary
A1: FY2025 summary
A3: Revenue | B3: =Revenue!B15
A4: Gross profit | B4: =SUM(Revenue!B13:M13)
A5: Operating cost | B5: =Costs!B15
A6: EBITDA | B6: =B4-B5
A8: EBITDA margin | B8: =B6/B3
A10: Ending customers | B10: =Revenue!M9
A11: Revenue per head | B11: =B3/Inputs!$B$8
A13: Prior-year revenue | B13: ='[Plan_2024.xlsx]Summary'!$B$3
A14: Growth vs prior year | B14: =B3/B13-1
A16: Legacy check | B16: =#REF!*1.15

Sheet Scratch
A1: Old upside case — do not use
A3: Month | B3: Jan | C3: Feb | D3: Mar
B4: =Revenue!B12-Revenue!B13 | C4: =Revenue!C12-Revenue!C13 | D4: =Revenue!D12-Revenue!D13
B5: =Revenue!B12-Revenue!B13 | C5: =Revenue!C12-Revenue!C13 | D5: =Revenue!D12-Revenue!D13
B6: =Revenue!B12-Revenue!B13 | C6: =Revenue!C12-Revenue!C13 | D6: =Revenue!D12-Revenue!D13
B7: =Revenue!B12-Revenue!B13 | C7: =Revenue!C12-Revenue!C13 | D7: =Revenue!D12-Revenue!D13
B8: =Revenue!B12-Revenue!B13 | C8: =Revenue!C12-Revenue!C13 | D8: =Revenue!D12-Revenue!D13
B9: =Revenue!B12-Revenue!B13 | C9: =Revenue!C12-Revenue!C13 | D9: =Revenue!D12-Revenue!D13
